raw_image_processor/__init__.py
raw_image_processor/convert_images.py
raw_image_processor-0.1.4.dist-info/LICENSE
raw_image_processor-0.1.4.dist-info/METADATA
raw_image_processor-0.1.4.dist-info/WHEEL
raw_image_processor-0.1.4.dist-info/entry_points.txt
raw_image_processor-0.1.4.dist-info/RECORD
